gofile_api/__init__.py
gofile_api/api.py
gofile_api/consts.py
gofile_api/exceptions.py
gofile_api-0.1.0.dist-info/LICENSE
gofile_api-0.1.0.dist-info/METADATA
gofile_api-0.1.0.dist-info/WHEEL
gofile_api-0.1.0.dist-info/top_level.txt
gofile_api-0.1.0.dist-info/RECORD
