Metadata-Version: 2.1
Name: gofile-api
Version: 0.1.0
Summary: A python library for communicating with the Gofile API.
Home-page: https://github.com/objectiveSquid/GoFile-API
Author: Magnus Zahle
Author-email: objectivesquid@outlook.com
License: MIT
Keywords: python,gofile,api,gofileio,gofile.io
Classifier: Development Status :: 5 - Production/Stable
Classifier: Intended Audience :: Developers
Classifier: License :: OSI Approved :: MIT License
Classifier: Programming Language :: Python :: 3 :: Only
Classifier: Natural Language :: English
License-File: LICENSE
Requires-Dist: requests
